addition_shantanu/__init__.py
addition_shantanu/tyrue.py
addition_shantanu-0.0.2.dist-info/LICENSE.txt
addition_shantanu-0.0.2.dist-info/METADATA
addition_shantanu-0.0.2.dist-info/WHEEL
addition_shantanu-0.0.2.dist-info/top_level.txt
addition_shantanu-0.0.2.dist-info/RECORD
